{
  "generated_at": "2026-05-22T23:16:32.500805+05:30",
  "date": "2026-05-22",
  "display_date": "Friday, 22 May 2026",
  "sample_mode": false,
  "regime": {
    "name": "BEAR",
    "scalar": 0.1,
    "exposure_pct": 10
  },
  "macro": {
    "nifty_close": 22651.3,
    "nifty_200dma": 23059.48,
    "nifty_dma_pct": -1.8,
    "india_vix": 17.9,
    "usdinr": 96.53,
    "usdinr_30d_move": 4.39,
    "fii_net": -4440.0,
    "dii_net": 6004.0
  },
  "pipeline_stats": {
    "total_universe": 418,
    "stage_1a_pass": 418,
    "stage_1b_pass": 414,
    "stage_1c_pass": 414,
    "stage_2_scored": 414,
    "has_fundamentals": 21,
    "date": "2026-05-22",
    "regime": "BEAR",
    "vix": 17.9,
    "high_vix_mode": false
  },
  "factor_weights": {
    "rs": 0.35,
    "del": 0.2,
    "vam": 0.2,
    "rev": 0.25
  },
  "bullish": [
    {
      "symbol": "HONASA",
      "close": 384.35,
      "return_1d": 6.6,
      "return_1w": 10.4,
      "return_3m": 28.0,
      "mrs": 24.327,
      "deliv": 2.6097,
      "vam": 1.0073,
      "fq": 0.0,
      "rev": 2.2446,
      "atr14": 13.24,
      "effective_atr_stop": 13.2357,
      "adt_20d": 1414027734.3681,
      "sector": "Fast Moving Consumer Goods",
      "m_score": 0,
      "ccr": 0,
      "has_fundamentals": false,
      "forensic_clean": true,
      "high_52w_pct": 0.954,
      "n_factors": 4,
      "mrs_rank": 0.9758,
      "deliv_rank": 0.9831,
      "vam_rank": 0.8986,
      "rev_rank": 0.9469,
      "confidence": 95.4589,
      "data_confidence": 1.0,
      "forensic_penalty": 1.0,
      "adj_confidence": 95.4589,
      "target_high": 424.06,
      "stop_loss": 344.64,
      "w20_high": 402.8,
      "w20_low": 260.8,
      "rs_slope": 8.57,
      "proximity_to_high": 95.4,
      "avg_daily_range_pct": 3.17,
      "deliv_pct": 7.61
    },
    {
      "symbol": "SCHNEIDER",
      "close": 1307.6,
      "return_1d": -1.3,
      "return_1w": 8.9,
      "return_3m": 53.9,
      "mrs": 29.7633,
      "deliv": 1.0556,
      "vam": 1.5466,
      "fq": 0.0,
      "rev": 2.34,
      "atr14": 74.65,
      "effective_atr_stop": 74.65,
      "adt_20d": 260673093.328,
      "sector": "Capital Goods",
      "m_score": 0,
      "ccr": 0,
      "has_fundamentals": false,
      "forensic_clean": true,
      "high_52w_pct": 0.954,
      "n_factors": 4,
      "mrs_rank": 0.9928,
      "deliv_rank": 0.8261,
      "vam_rank": 0.9614,
      "rev_rank": 0.9783,
      "confidence": 94.9517,
      "data_confidence": 1.0,
      "forensic_penalty": 1.0,
      "adj_confidence": 94.9517,
      "target_high": 1531.55,
      "stop_loss": 1083.65,
      "w20_high": 1370.0,
      "w20_low": 571.85,
      "rs_slope": 3.42,
      "proximity_to_high": 95.4,
      "avg_daily_range_pct": 5.89,
      "deliv_pct": 51.54
    },
    {
      "symbol": "POWERINDIA",
      "close": 35555.0,
      "return_1d": -2.5,
      "return_1w": 8.4,
      "return_3m": 54.7,
      "mrs": 29.7633,
      "deliv": 0.6678,
      "vam": 2.2109,
      "fq": 0.0,
      "rev": 2.5,
      "atr14": 1367.14,
      "effective_atr_stop": 1367.1429,
      "adt_20d": 4522285763.05,
      "sector": "Capital Goods",
      "m_score": 0,
      "ccr": 0,
      "has_fundamentals": false,
      "forensic_clean": true,
      "high_52w_pct": 0.967,
      "n_factors": 4,
      "mrs_rank": 0.9928,
      "deliv_rank": 0.6329,
      "vam_rank": 0.9928,
      "rev_rank": 0.9855,
      "confidence": 91.8961,
      "data_confidence": 1.0,
      "forensic_penalty": 1.0,
      "adj_confidence": 91.8961,
      "target_high": 39656.43,
      "stop_loss": 31453.57,
      "w20_high": 36750.0,
      "w20_low": 16111.0,
      "rs_slope": 9.28,
      "proximity_to_high": 96.7,
      "avg_daily_range_pct": 3.73,
      "deliv_pct": 38.06
    },
    {
      "symbol": "ACMESOLAR",
      "close": 290.2,
      "return_1d": 2.7,
      "return_1w": 5.3,
      "return_3m": 23.6,
      "mrs": 13.9237,
      "deliv": 1.4356,
      "vam": 0.5563,
      "fq": 0.0,
      "rev": 2.0981,
      "atr14": 12.24,
      "effective_atr_stop": 12.2357,
      "adt_20d": 435542594.8882,
      "sector": "Power",
      "m_score": 0,
      "ccr": 0,
      "has_fundamentals": false,
      "forensic_clean": true,
      "high_52w_pct": 0.895,
      "n_factors": 4,
      "mrs_rank": 0.8986,
      "deliv_rank": 0.8961,
      "vam_rank": 0.7947,
      "rev_rank": 0.901,
      "confidence": 87.7899,
      "data_confidence": 1.0,
      "forensic_penalty": 1.0,
      "adj_confidence": 87.7899,
      "target_high": 326.91,
      "stop_loss": 253.49,
      "w20_high": 316.9,
      "w20_low": 195.9,
      "rs_slope": 5.14,
      "proximity_to_high": 91.6,
      "avg_daily_range_pct": 4.08,
      "deliv_pct": 41.31
    },
    {
      "symbol": "DEEPAKFERT",
      "close": 1473.9,
      "return_1d": 6.5,
      "return_1w": 15.8,
      "return_3m": 42.5,
      "mrs": 29.7633,
      "deliv": 2.3188,
      "vam": -0.2078,
      "fq": 0.0,
      "rev": 2.4404,
      "atr14": 60.31,
      "effective_atr_stop": 60.3071,
      "adt_20d": 641907584.724,
      "sector": "Chemicals",
      "m_score": 0,
      "ccr": 0,
      "has_fundamentals": false,
      "forensic_clean": true,
      "high_52w_pct": 0.829,
      "n_factors": 4,
      "mrs_rank": 0.9928,
      "deliv_rank": 0.971,
      "vam_rank": 0.4034,
      "rev_rank": 0.9807,
      "confidence": 86.7512,
      "data_confidence": 1.0,
      "forensic_penalty": 1.0,
      "adj_confidence": 86.7512,
      "target_high": 1654.82,
      "stop_loss": 1292.98,
      "w20_high": 1485.0,
      "w20_low": 866.4,
      "rs_slope": 11.79,
      "proximity_to_high": 99.3,
      "avg_daily_range_pct": 4.14,
      "deliv_pct": 25.99
    },
    {
      "symbol": "APOLLOHOSP",
      "close": 8362.5,
      "return_1d": 0.6,
      "return_1w": 4.3,
      "return_3m": 10.0,
      "mrs": 10.8873,
      "deliv": 1.3396,
      "vam": 0.5995,
      "fq": 0.0,
      "rev": 2.1,
      "atr14": 164.0,
      "effective_atr_stop": 164.0,
      "adt_20d": 3668570069.395,
      "sector": "Healthcare",
      "m_score": 0,
      "ccr": 0,
      "has_fundamentals": false,
      "forensic_clean": true,
      "high_52w_pct": 0.991,
      "n_factors": 4,
      "mrs_rank": 0.843,
      "deliv_rank": 0.8841,
      "vam_rank": 0.8043,
      "rev_rank": 0.907,
      "confidence": 85.9481,
      "data_confidence": 1.0,
      "forensic_penalty": 1.0,
      "adj_confidence": 85.9481,
      "target_high": 8854.5,
      "stop_loss": 7870.5,
      "w20_high": 8440.5,
      "w20_low": 6696.5,
      "rs_slope": 3.46,
      "proximity_to_high": 99.1,
      "avg_daily_range_pct": 1.93,
      "deliv_pct": 54.73
    },
    {
      "symbol": "NEULANDLAB",
      "close": 16693.0,
      "return_1d": 0.0,
      "return_1w": 2.2,
      "return_3m": 22.1,
      "mrs": 17.3651,
      "deliv": 0.5673,
      "vam": 0.849,
      "fq": 0.0,
      "rev": 2.5254,
      "atr14": 757.71,
      "effective_atr_stop": 757.7143,
      "adt_20d": 1396067924.0075,
      "sector": "Healthcare",
      "m_score": 0,
      "ccr": 0,
      "has_fundamentals": false,
      "forensic_clean": true,
      "high_52w_pct": 0.845,
      "n_factors": 4,
      "mrs_rank": 0.9396,
      "deliv_rank": 0.529,
      "vam_rank": 0.8768,
      "rev_rank": 0.9879,
      "confidence": 85.7005,
      "data_confidence": 1.0,
      "forensic_penalty": 1.0,
      "adj_confidence": 85.7005,
      "target_high": 18966.14,
      "stop_loss": 14419.86,
      "w20_high": 18305.0,
      "w20_low": 11500.0,
      "rs_slope": 0.62,
      "proximity_to_high": 91.2,
      "avg_daily_range_pct": 4.53,
      "deliv_pct": 37.89
    },
    {
      "symbol": "TIMKEN",
      "close": 3750.2,
      "return_1d": 1.0,
      "return_1w": 9.2,
      "return_3m": 18.7,
      "mrs": 13.1681,
      "deliv": 0.9162,
      "vam": 0.4963,
      "fq": 0.0,
      "rev": 2.1528,
      "atr14": 122.14,
      "effective_atr_stop": 122.1429,
      "adt_20d": 313059613.1272,
      "sector": "Capital Goods",
      "m_score": 0,
      "ccr": 0,
      "has_fundamentals": false,
      "forensic_clean": true,
      "high_52w_pct": 0.996,
      "n_factors": 4,
      "mrs_rank": 0.8768,
      "deliv_rank": 0.7754,
      "vam_rank": 0.7778,
      "rev_rank": 0.9275,
      "confidence": 84.9396,
      "data_confidence": 1.0,
      "forensic_penalty": 1.0,
      "adj_confidence": 84.9396,
      "target_high": 4116.63,
      "stop_loss": 3383.77,
      "w20_high": 3765.0,
      "w20_low": 2890.8,
      "rs_slope": 6.2,
      "proximity_to_high": 99.6,
      "avg_daily_range_pct": 3.21,
      "deliv_pct": 54.61
    },
    {
      "symbol": "TATACOMM",
      "close": 1964.0,
      "return_1d": 3.6,
      "return_1w": 17.7,
      "return_3m": 18.9,
      "mrs": 23.9552,
      "deliv": 2.5698,
      "vam": -0.1162,
      "fq": 0.0,
      "rev": 2.0,
      "atr14": 69.71,
      "effective_atr_stop": 69.7143,
      "adt_20d": 1256029668.088,
      "sector": "Telecommunication",
      "m_score": 0,
      "ccr": 0,
      "has_fundamentals": false,
      "forensic_clean": true,
      "high_52w_pct": 0.98,
      "n_factors": 4,
      "mrs_rank": 0.971,
      "deliv_rank": 0.9807,
      "vam_rank": 0.4614,
      "rev_rank": 0.8611,
      "confidence": 84.3539,
      "data_confidence": 1.0,
      "forensic_penalty": 1.0,
      "adj_confidence": 84.3539,
      "target_high": 2173.14,
      "stop_loss": 1754.86,
      "w20_high": 1979.0,
      "w20_low": 1322.5,
      "rs_slope": 16.9,
      "proximity_to_high": 99.2,
      "avg_daily_range_pct": 3.79,
      "deliv_pct": 40.4
    },
    {
      "symbol": "ENDURANCE",
      "close": 2721.8,
      "return_1d": 3.8,
      "return_1w": 7.7,
      "return_3m": 7.8,
      "mrs": 10.7619,
      "deliv": 1.4343,
      "vam": 0.2013,
      "fq": 0.0,
      "rev": 2.2117,
      "atr14": 110.18,
      "effective_atr_stop": 110.1786,
      "adt_20d": 457128584.6708,
      "sector": "Automobile and Auto Components",
      "m_score": 0,
      "ccr": 0,
      "has_fundamentals": false,
      "forensic_clean": true,
      "high_52w_pct": 0.884,
      "n_factors": 4,
      "mrs_rank": 0.8333,
      "deliv_rank": 0.8937,
      "vam_rank": 0.6449,
      "rev_rank": 0.9396,
      "confidence": 83.43,
      "data_confidence": 1.0,
      "forensic_penalty": 1.0,
      "adj_confidence": 83.43,
      "target_high": 3052.34,
      "stop_loss": 2391.26,
      "w20_high": 2756.6,
      "w20_low": 2142.8,
      "rs_slope": 6.8,
      "proximity_to_high": 98.7,
      "avg_daily_range_pct": 3.9,
      "deliv_pct": 34.97
    }
  ],
  "bearish": [
    {
      "symbol": "AFCONS",
      "bearish_score": 56.5,
      "close": 300.25,
      "return_1d": -0.3,
      "return_1w": -5.4,
      "return_3m": -7.4,
      "return_6m": -24.2,
      "sector": "Construction",
      "m_score": -3.05,
      "ccr": 0.47,
      "mansfield_rs": -5.7,
      "below_200dma": true,
      "dma_pct": -20.2,
      "lvgi": 1.55,
      "lvgi_rising": true,
      "de_ratio": 0.67,
      "qoq_rev_change": -18.9,
      "neg_revision": false,
      "revision_proxy": 1.636,
      "vol_rising": true,
      "signal": "SHORT"
    },
    {
      "symbol": "SWIGGY",
      "bearish_score": 53.3,
      "close": 249.95,
      "return_1d": -0.3,
      "return_1w": -1.6,
      "return_3m": -24.4,
      "return_6m": -36.5,
      "sector": "Consumer Services",
      "m_score": -2.95,
      "ccr": 0.0,
      "mansfield_rs": -15.9,
      "below_200dma": true,
      "dma_pct": -30.5,
      "lvgi": 2.44,
      "lvgi_rising": true,
      "de_ratio": 0.14,
      "qoq_rev_change": 44.7,
      "neg_revision": false,
      "revision_proxy": 0.79,
      "vol_rising": false,
      "signal": "SHORT"
    },
    {
      "symbol": "HEXT",
      "bearish_score": 39.6,
      "close": 514.05,
      "return_1d": 2.2,
      "return_1w": 5.6,
      "return_3m": -13.5,
      "return_6m": -26.8,
      "sector": "Information Technology",
      "m_score": 1.6113979999999998e+19,
      "ccr": -0.01,
      "mansfield_rs": -3.3,
      "below_200dma": true,
      "dma_pct": -19.9,
      "lvgi": 1.26,
      "lvgi_rising": true,
      "de_ratio": 0.11,
      "qoq_rev_change": 0.0,
      "neg_revision": false,
      "revision_proxy": 0.895,
      "vol_rising": false,
      "signal": "CAUTION"
    },
    {
      "symbol": "PGHH",
      "bearish_score": 39.1,
      "close": 9585.0,
      "return_1d": -0.8,
      "return_1w": -0.9,
      "return_3m": -17.3,
      "return_6m": -25.7,
      "sector": "Fast Moving Consumer Goods",
      "m_score": -1.89,
      "ccr": 0.14,
      "mansfield_rs": -11.0,
      "below_200dma": true,
      "dma_pct": -21.2,
      "lvgi": 0.8,
      "lvgi_rising": false,
      "de_ratio": 0.0,
      "qoq_rev_change": 1.1,
      "neg_revision": false,
      "revision_proxy": 0.818,
      "vol_rising": false,
      "signal": "CAUTION"
    },
    {
      "symbol": "TCS",
      "bearish_score": 37.0,
      "close": 2317.3,
      "return_1d": -0.4,
      "return_1w": 1.5,
      "return_3m": -14.7,
      "return_6m": -24.9,
      "sector": "Information Technology",
      "m_score": -2.58,
      "ccr": 0.59,
      "mansfield_rs": -12.8,
      "below_200dma": true,
      "dma_pct": -20.1,
      "lvgi": 1.25,
      "lvgi_rising": true,
      "de_ratio": 0.11,
      "qoq_rev_change": 10.5,
      "neg_revision": false,
      "revision_proxy": 0.459,
      "vol_rising": false,
      "signal": "CAUTION"
    },
    {
      "symbol": "VENTIVE",
      "bearish_score": 32.9,
      "close": 619.75,
      "return_1d": -1.1,
      "return_1w": -2.1,
      "return_3m": -15.3,
      "return_6m": -16.1,
      "sector": "Consumer Services",
      "m_score": -2.35,
      "ccr": 0.28,
      "mansfield_rs": -8.4,
      "below_200dma": true,
      "dma_pct": -12.6,
      "lvgi": 0.66,
      "lvgi_rising": false,
      "de_ratio": 0.47,
      "qoq_rev_change": 11.6,
      "neg_revision": false,
      "revision_proxy": 1.384,
      "vol_rising": false,
      "signal": "CAUTION"
    },
    {
      "symbol": "BAJAJHFL",
      "bearish_score": 30.8,
      "close": 83.07,
      "return_1d": 0.4,
      "return_1w": -0.9,
      "return_3m": -6.4,
      "return_6m": -22.1,
      "sector": "Financial Services",
      "m_score": -2.64,
      "ccr": -3.69,
      "mansfield_rs": -4.2,
      "below_200dma": true,
      "dma_pct": -15.2,
      "lvgi": 1.39,
      "lvgi_rising": true,
      "de_ratio": 4.6,
      "qoq_rev_change": 20.5,
      "neg_revision": false,
      "revision_proxy": 1.5,
      "vol_rising": false,
      "signal": "CAUTION"
    },
    {
      "symbol": "INFY",
      "bearish_score": 27.1,
      "close": 1174.5,
      "return_1d": -0.6,
      "return_1w": 2.8,
      "return_3m": -15.6,
      "return_6m": -21.0,
      "sector": "Information Technology",
      "m_score": -2.36,
      "ccr": 0.7,
      "mansfield_rs": -13.2,
      "below_200dma": true,
      "dma_pct": -18.8,
      "lvgi": 1.01,
      "lvgi_rising": false,
      "de_ratio": 0.1,
      "qoq_rev_change": 6.6,
      "neg_revision": false,
      "revision_proxy": 0.6,
      "vol_rising": false,
      "signal": "CAUTION"
    },
    {
      "symbol": "LTM",
      "bearish_score": 26.7,
      "close": 4007.8,
      "return_1d": -3.0,
      "return_1w": -1.6,
      "return_3m": -22.4,
      "return_6m": -30.4,
      "sector": "Information Technology",
      "m_score": -2.88,
      "ccr": 1.33,
      "mansfield_rs": -16.8,
      "below_200dma": true,
      "dma_pct": -23.6,
      "lvgi": 1.03,
      "lvgi_rising": false,
      "de_ratio": 0.1,
      "qoq_rev_change": 16.9,
      "neg_revision": false,
      "revision_proxy": 0.602,
      "vol_rising": false,
      "signal": "CAUTION"
    },
    {
      "symbol": "RECLTD",
      "bearish_score": 20.5,
      "close": 336.95,
      "return_1d": 1.0,
      "return_1w": 1.0,
      "return_3m": -6.0,
      "return_6m": -6.2,
      "sector": "Financial Services",
      "m_score": -3.41,
      "ccr": 3.72635e+19,
      "mansfield_rs": -4.3,
      "below_200dma": true,
      "dma_pct": -6.7,
      "lvgi": 1.06,
      "lvgi_rising": true,
      "de_ratio": 6.05,
      "qoq_rev_change": 0.1,
      "neg_revision": false,
      "revision_proxy": 0.857,
      "vol_rising": false,
      "signal": "CAUTION"
    }
  ]
}