{
  "generated_at": "2026-03-24T22:31:05.879555+05:30",
  "date": "2026-03-24",
  "display_date": "Tuesday, 24 Mar 2026",
  "sample_mode": false,
  "regime": {
    "name": "BEAR",
    "scalar": 0.1,
    "exposure_pct": 10
  },
  "macro": {
    "nifty_close": 21067.0,
    "nifty_200dma": 23233.66,
    "nifty_dma_pct": -9.3,
    "india_vix": 24.7,
    "usdinr": 93.9,
    "usdinr_30d_move": 3.38,
    "fii_net": -8010.0,
    "dii_net": 5867.0
  },
  "pipeline_stats": {
    "total_universe": 420,
    "stage_1a_pass": 419,
    "stage_1b_pass": 413,
    "stage_1c_pass": 413,
    "stage_2_scored": 413,
    "has_fundamentals": 27,
    "date": "2026-03-24",
    "regime": "BEAR",
    "vix": 24.7,
    "high_vix_mode": true
  },
  "factor_weights": {
    "rs": 0.35,
    "del": 0.2,
    "vam": 0.2,
    "rev": 0.25
  },
  "bullish": [
    {
      "symbol": "POWERINDIA",
      "close": 25025.0,
      "return_1d": 3.2,
      "return_1w": 0.2,
      "return_3m": 35.5,
      "mrs": 27.2801,
      "deliv": 0.8379,
      "vam": 2.3452,
      "fq": 0.0,
      "rev": 1.875,
      "atr14": 684.5,
      "effective_atr_stop": 684.5,
      "adt_20d": 3203700450.055,
      "sector": "Capital Goods",
      "m_score": 0,
      "ccr": 0,
      "has_fundamentals": false,
      "forensic_clean": true,
      "high_52w_pct": 0.951,
      "n_factors": 4,
      "mrs_rank": 0.9988,
      "deliv_rank": 0.6005,
      "vam_rank": 0.9758,
      "rev_rank": 0.9019,
      "confidence": 89.0315,
      "data_confidence": 1.0,
      "forensic_penalty": 1.0,
      "adj_confidence": 89.0315,
      "target_high": 27078.5,
      "stop_loss": 22971.5,
      "w20_high": 26325.0,
      "w20_low": 16111.0,
      "rs_slope": 1.27,
      "proximity_to_high": 95.1,
      "avg_daily_range_pct": 3.5,
      "deliv_pct": 36.71
    },
    {
      "symbol": "POWERGRID",
      "close": 299.0,
      "return_1d": -1.0,
      "return_1w": -0.1,
      "return_3m": 12.0,
      "mrs": 17.7909,
      "deliv": 1.3665,
      "vam": 0.3921,
      "fq": 0.0,
      "rev": 2.5975,
      "atr14": 6.41,
      "effective_atr_stop": 6.4125,
      "adt_20d": 5458184091.9489,
      "sector": "Power",
      "m_score": 0,
      "ccr": 0,
      "has_fundamentals": false,
      "forensic_clean": true,
      "high_52w_pct": 0.929,
      "n_factors": 4,
      "mrs_rank": 0.9661,
      "deliv_rank": 0.8571,
      "vam_rank": 0.6102,
      "rev_rank": 1.0,
      "confidence": 88.1598,
      "data_confidence": 1.0,
      "forensic_penalty": 1.0,
      "adj_confidence": 88.1598,
      "target_high": 318.24,
      "stop_loss": 279.76,
      "w20_high": 311.7,
      "w20_low": 250.0,
      "rs_slope": 0.17,
      "proximity_to_high": 95.9,
      "avg_daily_range_pct": 2.8,
      "deliv_pct": 51.62
    },
    {
      "symbol": "LUPIN",
      "close": 2331.8,
      "return_1d": 1.5,
      "return_1w": 1.3,
      "return_3m": 10.3,
      "mrs": 18.5881,
      "deliv": 1.5643,
      "vam": 0.5228,
      "fq": 0.0,
      "rev": 1.8,
      "atr14": 37.56,
      "effective_atr_stop": 37.56,
      "adt_20d": 2297924230.58,
      "sector": "Healthcare",
      "m_score": 0,
      "ccr": 0,
      "has_fundamentals": false,
      "forensic_clean": true,
      "high_52w_pct": 0.981,
      "n_factors": 4,
      "mrs_rank": 0.9758,
      "deliv_rank": 0.908,
      "vam_rank": 0.6755,
      "rev_rank": 0.8729,
      "confidence": 87.6453,
      "data_confidence": 1.0,
      "forensic_penalty": 1.0,
      "adj_confidence": 87.6453,
      "target_high": 2444.48,
      "stop_loss": 2219.12,
      "w20_high": 2377.6,
      "w20_low": 1926.9,
      "rs_slope": 1.46,
      "proximity_to_high": 98.1,
      "avg_daily_range_pct": 2.04,
      "deliv_pct": 60.97
    },
    {
      "symbol": "JBCHEPHARM",
      "close": 2076.8,
      "return_1d": -0.2,
      "return_1w": -1.9,
      "return_3m": 15.1,
      "mrs": 20.3319,
      "deliv": 0.8349,
      "vam": 1.3719,
      "fq": 0.0,
      "rev": 1.8624,
      "atr14": 38.98,
      "effective_atr_stop": 38.98,
      "adt_20d": 779650531.968,
      "sector": "Healthcare",
      "m_score": 0,
      "ccr": 0,
      "has_fundamentals": false,
      "forensic_clean": true,
      "high_52w_pct": 0.946,
      "n_factors": 4,
      "mrs_rank": 0.9806,
      "deliv_rank": 0.5981,
      "vam_rank": 0.8886,
      "rev_rank": 0.8935,
      "confidence": 86.3923,
      "data_confidence": 1.0,
      "forensic_penalty": 1.0,
      "adj_confidence": 86.3923,
      "target_high": 2193.74,
      "stop_loss": 1959.86,
      "w20_high": 2195.0,
      "w20_low": 1675.0,
      "rs_slope": -1.29,
      "proximity_to_high": 94.6,
      "avg_daily_range_pct": 2.67,
      "deliv_pct": 56.56
    },
    {
      "symbol": "GRANULES",
      "close": 606.35,
      "return_1d": 4.5,
      "return_1w": 3.3,
      "return_3m": -1.4,
      "mrs": 15.7423,
      "deliv": 1.6732,
      "vam": 0.6625,
      "fq": 0.0,
      "rev": 1.666,
      "atr14": 15.14,
      "effective_atr_stop": 15.14,
      "adt_20d": 433226648.9155,
      "sector": "Healthcare",
      "m_score": 0,
      "ccr": 0,
      "has_fundamentals": false,
      "forensic_clean": true,
      "high_52w_pct": 0.967,
      "n_factors": 4,
      "mrs_rank": 0.9322,
      "deliv_rank": 0.9177,
      "vam_rank": 0.7361,
      "rev_rank": 0.8232,
      "confidence": 86.2833,
      "data_confidence": 1.0,
      "forensic_penalty": 1.0,
      "adj_confidence": 86.2833,
      "target_high": 651.77,
      "stop_loss": 560.93,
      "w20_high": 627.0,
      "w20_low": 529.85,
      "rs_slope": 6.01,
      "proximity_to_high": 96.7,
      "avg_daily_range_pct": 3.17,
      "deliv_pct": 52.91
    },
    {
      "symbol": "APOLLOHOSP",
      "close": 7413.0,
      "return_1d": 3.8,
      "return_1w": -0.8,
      "return_3m": 4.8,
      "mrs": 11.1543,
      "deliv": 1.5502,
      "vam": 0.9627,
      "fq": 0.0,
      "rev": 1.6667,
      "atr14": 136.35,
      "effective_atr_stop": 136.35,
      "adt_20d": 3448743607.76,
      "sector": "Healthcare",
      "m_score": 0,
      "ccr": 0,
      "has_fundamentals": false,
      "forensic_clean": true,
      "high_52w_pct": 0.915,
      "n_factors": 4,
      "mrs_rank": 0.8886,
      "deliv_rank": 0.9056,
      "vam_rank": 0.8136,
      "rev_rank": 0.8305,
      "confidence": 86.247,
      "data_confidence": 1.0,
      "forensic_penalty": 1.0,
      "adj_confidence": 86.247,
      "target_high": 7822.05,
      "stop_loss": 7003.95,
      "w20_high": 7891.0,
      "w20_low": 6696.5,
      "rs_slope": -1.16,
      "proximity_to_high": 93.9,
      "avg_daily_range_pct": 2.22,
      "deliv_pct": 53.77
    },
    {
      "symbol": "KIRLOSENG",
      "close": 1327.9,
      "return_1d": 3.1,
      "return_1w": -7.5,
      "return_3m": 2.3,
      "mrs": 9.3148,
      "deliv": 0.8234,
      "vam": 2.1079,
      "fq": 0.0,
      "rev": 2.3707,
      "atr14": 47.22,
      "effective_atr_stop": 47.225,
      "adt_20d": 526899648.5853,
      "sector": "Capital Goods",
      "m_score": 0,
      "ccr": 0,
      "has_fundamentals": false,
      "forensic_clean": true,
      "high_52w_pct": 0.868,
      "n_factors": 4,
      "mrs_rank": 0.8571,
      "deliv_rank": 0.5932,
      "vam_rank": 0.9637,
      "rev_rank": 0.9879,
      "confidence": 85.8354,
      "data_confidence": 1.0,
      "forensic_penalty": 1.0,
      "adj_confidence": 85.8354,
      "target_high": 1469.58,
      "stop_loss": 1186.23,
      "w20_high": 1530.0,
      "w20_low": 933.2,
      "rs_slope": -7.89,
      "proximity_to_high": 86.8,
      "avg_daily_range_pct": 4.73,
      "deliv_pct": 39.55
    },
    {
      "symbol": "GESHIP",
      "close": 1398.7,
      "return_1d": 2.8,
      "return_1w": -2.9,
      "return_3m": 26.1,
      "mrs": 27.2801,
      "deliv": 0.9848,
      "vam": 1.3823,
      "fq": 0.0,
      "rev": 1.511,
      "atr14": 48.72,
      "effective_atr_stop": 48.72,
      "adt_20d": 958845792.1243,
      "sector": "Services",
      "m_score": 0,
      "ccr": 0,
      "has_fundamentals": false,
      "forensic_clean": true,
      "high_52w_pct": 0.927,
      "n_factors": 4,
      "mrs_rank": 0.9988,
      "deliv_rank": 0.7022,
      "vam_rank": 0.8935,
      "rev_rank": 0.7433,
      "confidence": 85.454,
      "data_confidence": 1.0,
      "forensic_penalty": 1.0,
      "adj_confidence": 85.454,
      "target_high": 1544.86,
      "stop_loss": 1252.54,
      "w20_high": 1509.0,
      "w20_low": 1035.1,
      "rs_slope": -1.94,
      "proximity_to_high": 92.7,
      "avg_daily_range_pct": 4.2,
      "deliv_pct": 60.81
    },
    {
      "symbol": "TORNTPHARM",
      "close": 4256.6,
      "return_1d": 1.0,
      "return_1w": -0.8,
      "return_3m": 11.4,
      "mrs": 17.1211,
      "deliv": 0.7728,
      "vam": 1.8123,
      "fq": 0.0,
      "rev": 1.6667,
      "atr14": 73.69,
      "effective_atr_stop": 73.69,
      "adt_20d": 1637135247.8122,
      "sector": "Healthcare",
      "m_score": 0,
      "ccr": 0,
      "has_fundamentals": false,
      "forensic_clean": true,
      "high_52w_pct": 0.95,
      "n_factors": 4,
      "mrs_rank": 0.9564,
      "deliv_rank": 0.5521,
      "vam_rank": 0.9443,
      "rev_rank": 0.8305,
      "confidence": 84.1646,
      "data_confidence": 1.0,
      "forensic_penalty": 1.0,
      "adj_confidence": 84.1646,
      "target_high": 4477.67,
      "stop_loss": 4035.53,
      "w20_high": 4482.9,
      "w20_low": 3532.6,
      "rs_slope": -1.14,
      "proximity_to_high": 95.0,
      "avg_daily_range_pct": 2.47,
      "deliv_pct": 50.52
    },
    {
      "symbol": "CCL",
      "close": 1080.8,
      "return_1d": 1.2,
      "return_1w": 3.3,
      "return_3m": 11.9,
      "mrs": 21.1593,
      "deliv": 0.6269,
      "vam": 2.7848,
      "fq": 0.0,
      "rev": 1.7574,
      "atr14": 26.4,
      "effective_atr_stop": 26.4,
      "adt_20d": 305424988.2154,
      "sector": "Fast Moving Consumer Goods",
      "m_score": 0,
      "ccr": 0,
      "has_fundamentals": false,
      "forensic_clean": true,
      "high_52w_pct": 0.978,
      "n_factors": 4,
      "mrs_rank": 0.9879,
      "deliv_rank": 0.3632,
      "vam_rank": 0.9939,
      "rev_rank": 0.862,
      "confidence": 83.2688,
      "data_confidence": 1.0,
      "forensic_penalty": 1.0,
      "adj_confidence": 83.2688,
      "target_high": 1160.0,
      "stop_loss": 1001.6,
      "w20_high": 1105.0,
      "w20_low": 852.05,
      "rs_slope": 4.04,
      "proximity_to_high": 97.8,
      "avg_daily_range_pct": 3.52,
      "deliv_pct": 36.17
    }
  ],
  "bearish": [
    {
      "symbol": "SWIGGY",
      "bearish_score": 46.0,
      "close": 275.75,
      "return_1d": 1.2,
      "return_1w": -7.7,
      "return_3m": -31.9,
      "return_6m": -38.7,
      "sector": "Consumer Services",
      "m_score": -2.0812823664999997e+19,
      "ccr": 0.0,
      "mansfield_rs": -12.7,
      "below_200dma": true,
      "dma_pct": -27.7,
      "lvgi": 0.0,
      "lvgi_rising": false,
      "de_ratio": 0.0,
      "qoq_rev_change": 54.0,
      "neg_revision": false,
      "revision_proxy": 0.955,
      "vol_rising": false,
      "signal": "CAUTION"
    },
    {
      "symbol": "VMM",
      "bearish_score": 45.2,
      "close": 106.93,
      "return_1d": 7.3,
      "return_1w": -0.9,
      "return_3m": -21.8,
      "return_6m": -28.2,
      "sector": "Consumer Services",
      "m_score": -2.47,
      "ccr": 0.27,
      "mansfield_rs": -5.8,
      "below_200dma": true,
      "dma_pct": -20.4,
      "lvgi": 1.27,
      "lvgi_rising": true,
      "de_ratio": 0.27,
      "qoq_rev_change": 17.0,
      "neg_revision": false,
      "revision_proxy": 1.606,
      "vol_rising": true,
      "signal": "CAUTION"
    },
    {
      "symbol": "PGHH",
      "bearish_score": 44.8,
      "close": 9496.0,
      "return_1d": 0.4,
      "return_1w": -5.2,
      "return_3m": -26.9,
      "return_6m": -29.8,
      "sector": "Fast Moving Consumer Goods",
      "m_score": -1.99,
      "ccr": 0.14,
      "mansfield_rs": -12.8,
      "below_200dma": true,
      "dma_pct": -25.9,
      "lvgi": 0.67,
      "lvgi_rising": false,
      "de_ratio": 0.0,
      "qoq_rev_change": 1.1,
      "neg_revision": false,
      "revision_proxy": 0.761,
      "vol_rising": true,
      "signal": "CAUTION"
    },
    {
      "symbol": "AFCONS",
      "bearish_score": 41.7,
      "close": 277.0,
      "return_1d": 2.1,
      "return_1w": -3.8,
      "return_3m": -27.6,
      "return_6m": -39.7,
      "sector": "Construction",
      "m_score": -2.55,
      "ccr": 0.25,
      "mansfield_rs": -12.7,
      "below_200dma": true,
      "dma_pct": -30.3,
      "lvgi": 1.03,
      "lvgi_rising": false,
      "de_ratio": 0.66,
      "qoq_rev_change": -7.3,
      "neg_revision": false,
      "revision_proxy": 0.528,
      "vol_rising": false,
      "signal": "CAUTION"
    },
    {
      "symbol": "DIXON",
      "bearish_score": 41.3,
      "close": 10174.0,
      "return_1d": 2.8,
      "return_1w": -5.0,
      "return_3m": -20.7,
      "return_6m": -43.7,
      "sector": "Consumer Durables",
      "m_score": -2.67,
      "ccr": 0.38,
      "mansfield_rs": -6.2,
      "below_200dma": true,
      "dma_pct": -28.9,
      "lvgi": 0.85,
      "lvgi_rising": false,
      "de_ratio": 0.22,
      "qoq_rev_change": -7.5,
      "neg_revision": false,
      "revision_proxy": 1.2,
      "vol_rising": true,
      "signal": "CAUTION"
    },
    {
      "symbol": "TCS",
      "bearish_score": 39.9,
      "close": 2398.8,
      "return_1d": 0.6,
      "return_1w": -1.7,
      "return_3m": -27.5,
      "return_6m": -22.0,
      "sector": "Information Technology",
      "m_score": -2.7,
      "ccr": 0.75,
      "mansfield_rs": -11.1,
      "below_200dma": true,
      "dma_pct": -22.0,
      "lvgi": 1.08,
      "lvgi_rising": true,
      "de_ratio": 0.1,
      "qoq_rev_change": 4.4,
      "neg_revision": true,
      "revision_proxy": 0.256,
      "vol_rising": false,
      "signal": "CAUTION"
    },
    {
      "symbol": "HEXT",
      "bearish_score": 38.0,
      "close": 437.15,
      "return_1d": 0.3,
      "return_1w": 0.1,
      "return_3m": -40.8,
      "return_6m": -39.9,
      "sector": "Information Technology",
      "m_score": -2.6,
      "ccr": 1.7,
      "mansfield_rs": -25.2,
      "below_200dma": true,
      "dma_pct": -38.6,
      "lvgi": 1.2,
      "lvgi_rising": true,
      "de_ratio": 0.11,
      "qoq_rev_change": 18.5,
      "neg_revision": false,
      "revision_proxy": 0.696,
      "vol_rising": true,
      "signal": "CAUTION"
    },
    {
      "symbol": "SAGILITY",
      "bearish_score": 36.0,
      "close": 37.32,
      "return_1d": 2.7,
      "return_1w": -5.4,
      "return_3m": -29.0,
      "return_6m": -16.9,
      "sector": "Information Technology",
      "m_score": -1.97,
      "ccr": 0.76,
      "mansfield_rs": -13.5,
      "below_200dma": true,
      "dma_pct": -18.9,
      "lvgi": 0.94,
      "lvgi_rising": false,
      "de_ratio": 0.17,
      "qoq_rev_change": 61.1,
      "neg_revision": false,
      "revision_proxy": 1.074,
      "vol_rising": true,
      "signal": "CAUTION"
    },
    {
      "symbol": "IRFC",
      "bearish_score": 34.2,
      "close": 92.87,
      "return_1d": 3.8,
      "return_1w": -5.5,
      "return_3m": -23.5,
      "return_6m": -27.8,
      "sector": "Financial Services",
      "m_score": -2.21,
      "ccr": -15.75,
      "mansfield_rs": -9.6,
      "below_200dma": true,
      "dma_pct": -24.0,
      "lvgi": 1.04,
      "lvgi_rising": false,
      "de_ratio": 7.38,
      "qoq_rev_change": -3.5,
      "neg_revision": false,
      "revision_proxy": 1.25,
      "vol_rising": false,
      "signal": "CAUTION"
    },
    {
      "symbol": "BAJAJHFL",
      "bearish_score": 34.0,
      "close": 78.75,
      "return_1d": 0.3,
      "return_1w": -5.2,
      "return_3m": -17.8,
      "return_6m": -30.5,
      "sector": "Financial Services",
      "m_score": -2.14,
      "ccr": -3.67,
      "mansfield_rs": -6.1,
      "below_200dma": true,
      "dma_pct": -24.9,
      "lvgi": 1.12,
      "lvgi_rising": true,
      "de_ratio": 4.11,
      "qoq_rev_change": 21.8,
      "neg_revision": false,
      "revision_proxy": 1.185,
      "vol_rising": false,
      "signal": "CAUTION"
    }
  ]
}